or_gym/__init__.py
or_gym/utils.py
or_gym/version.py
or_gym/envs/__init__.py
or_gym/envs/env_list.py
or_gym/envs/registry.py
or_gym/envs/classic_or/__init__.py
or_gym/envs/classic_or/binpacking.py
or_gym/envs/classic_or/knapsack.py
or_gym/envs/classic_or/newsvendor.py
or_gym/envs/classic_or/tsp.py
or_gym/envs/classic_or/vehicle_routing.py
or_gym/envs/classic_or/vmpacking.py
or_gym/envs/finance/__init__.py
or_gym/envs/finance/portfolio_opt.py
or_gym/envs/supply_chain/__init__.py
or_gym/envs/supply_chain/inventory_management.py
or_gym/envs/supply_chain/network_management.py
or_gym-0.5.0.dist-info/METADATA
or_gym-0.5.0.dist-info/WHEEL
or_gym-0.5.0.dist-info/entry_points.txt
or_gym-0.5.0.dist-info/license_files/LICENSE
or_gym-0.5.0.dist-info/RECORD
