Metadata-Version: 2.1
Name: or-gym
Version: 0.5.0
Summary: OR-Gym: A set of environments for developing reinforcement learning agents for OR problems.
Project-URL: Bug Tracker, https://github.com/hubbs5/or-gym/issues
Project-URL: Homepage, https://github.com/hubbs5/or-gym
Author-email: Christian Hubbs <christiandhubbs@gmail.com>, Owais Sarwar <owais.sarwar@gmail.com>, Hector Perez <hdperez@cmu.edu>
License: MIT License
Classifier: License :: OSI Approved :: MIT License
Classifier: Operating System :: OS Independent
Classifier: Programming Language :: Python :: 3
Requires-Python: >=3.7
Requires-Dist: gym<=0.19.0
Requires-Dist: matplotlib>=3.1
Requires-Dist: networkx>=2.3
Requires-Dist: numpy>=1.16.1
Requires-Dist: pandas>=1.2
Requires-Dist: scipy>=1.0
